{"is_source_file": true, "format": "JavaScript (Node.js)", "description": "This source file defines Express.js route handlers for recommendations and role comparison APIs within a careers or job recommendation backend. It handles GET requests to fetch role recommendations based on persona data and POST requests to compare roles, utilizing several schemas for validation and interacting with repository and service layers.", "external_files": ["../utils/errors", "../repositories/holisticPersonaRepoAdapter", "../services/recommendationsService", "../schemas/holisticPersonaSchemas"], "external_methods": ["sendError", "recommendationsService.getRoleRecommendationsFromFinalPersona", "holisticPersonaRepo.upsertRecommendationsRoles", "parseWithZod", "enforceResponse", "holisticPersonaRepo.createRecommendationsCompare"], "published": ["router"], "classes": [], "methods": [{"name": "GET /api/recommendations/roles", "description": "Handles requests to fetch role recommendations based on the latest persona, with optional filtering and persistence of recommendations."}, {"name": "POST /api/recommendations/compare", "description": "Handles requests to compare two roles and store the comparison, returning a summary and differences."}], "calls": ["recommendationsService.getRoleRecommendationsFromFinalPersona", "holisticPersonaRepo.upsertRecommendationsRoles", "parseWithZod", "enforceResponse", "holisticPersonaRepo.createRecommendationsCompare", "sendError"], "search-terms": ["recommendations", "role comparisons", "holistic persona", "recommendationsService", "holisticPersonaRepoAdapter", "schemas", "recommendations endpoints"], "state": 2, "file_id": 133, "knowledge_revision": 544, "git_revision": "afeb0e01bc45c4d90484de2368197fad9b83cd74", "revision_history": [{"494": "778a707cc6455694d9de73b863e8468a0165979a"}, {"508": "bcce6b59014d13677a0a36f7eae7d70b937a091f"}, {"517": "4c1bc313efa910b45f5bdc59fa64d1d37857a849"}, {"544": "afeb0e01bc45c4d90484de2368197fad9b83cd74"}], "ctags": [{"_type": "tag", "name": "express", "path": "/home/kavia/workspace/code-generation/career-navigator-server/express_backend/src/routes/recommendations.js", "pattern": "/^const express = require('express');$/", "language": "JavaScript", "kind": "constant"}, {"_type": "tag", "name": "holisticPersonaRepo", "path": "/home/kavia/workspace/code-generation/career-navigator-server/express_backend/src/routes/recommendations.js", "pattern": "/^const holisticPersonaRepo = require('..\\/repositories\\/holisticPersonaRepoAdapter');$/", "language": "JavaScript", "kind": "constant"}, {"_type": "tag", "name": "recommendationsService", "path": "/home/kavia/workspace/code-generation/career-navigator-server/express_backend/src/routes/recommendations.js", "pattern": "/^const recommendationsService = require('..\\/services\\/recommendationsService');$/", "language": "JavaScript", "kind": "constant"}, {"_type": "tag", "name": "router", "path": "/home/kavia/workspace/code-generation/career-navigator-server/express_backend/src/routes/recommendations.js", "pattern": "/^const router = express.Router();$/", "language": "JavaScript", "kind": "constant"}], "hash": "c97b2a065d9c2e3527b54b01a9fdfebf", "format-version": 4, "code-base-name": "career-navigator-server", "filename": "express_backend/src/routes/recommendations.js"}