{"is_source_file": false, "format": "", "description": "", "external_files": [], "external_methods": [], "published": [], "classes": [], "methods": [], "calls": [], "search-terms": [], "state": 2, "file_id": 26, "knowledge_revision": 125, "git_revision": "7cb0bad2a89733f486f7dae70c5dfeecb335f996", "hash": "e4e609b63541d280911e0c4236a3f5ea", "format-version": 4, "code-base-name": "career-navigator-server", "filename": "express_backend/docs/roles-search-filters-debug.md", "revision_history": [{"125": "7cb0bad2a89733f486f7dae70c5dfeecb335f996"}]}