{"is_source_file": true, "format": "JavaScript", "description": "This file defines a schema self-healing mechanism for a MySQL database. It includes helper functions to check for the existence of columns, indexes, and tables, and functions to add missing columns and indexes to specific tables ('persona_drafts' and 'persona_final') in a runtime-safe manner. The main exported function 'ensureMysqlSchemaCompatible' performs checks and applies updates if needed, ensuring the schema aligns with application expectations without causing errors during server startup.", "external_files": ["./connection"], "external_methods": ["dbQuery", "isDbConfigured", "getDbEngine"], "published": ["ensureMysqlSchemaCompatible"], "classes": [], "methods": [{"name": "_mysqlHasColumn(tableName, columnName)", "description": "Checks if a specific column exists in a given table by querying information_schema.columns.", "scope": "", "scopeKind": ""}, {"name": "_mysqlHasIndex(tableName, indexName)", "description": "Checks if a specific index exists on a table by querying information_schema.statistics.", "scope": "", "scopeKind": ""}, {"name": "_mysqlHasTable(tableName)", "description": "Checks if a table exists in the database by querying information_schema.tables.", "scope": "", "scopeKind": ""}, {"name": "_ensurePersonaDraftsPersonaIdColumnMysql()", "description": "Ensures the 'persona_id' column and related index exist in the 'persona_drafts' table, adding them if missing.", "scope": "", "scopeKind": ""}, {"name": "_ensurePersonaFinalPersonaIdColumnMysql()", "description": "Ensures the 'persona_id' column and related index exist in the 'persona_final' table, adding them if missing.", "scope": "", "scopeKind": ""}, {"name": "ensureMysqlSchemaCompatible()", "description": "Main function that performs runtime-safe schema checks and applies necessary modifications to align the database schema with application expectations.", "scope": "", "scopeKind": ""}], "calls": ["dbQuery", "isDbConfigured", "getDbEngine", "_mysqlHasTable", "_mysqlHasColumn", "_mysqlHasIndex", "_ensurePersonaDraftsPersonaIdColumnMysql", "_ensurePersonaFinalPersonaIdColumnMysql"], "search-terms": ["schema self-healing", "information_schema", "persona_id column", "MySQL schema upgrade", "runtime-safe schema modifications", "ensure schema compatibility", "persona_drafts", "persona_final", "self-healing database"], "state": 2, "file_id": 31, "knowledge_revision": 152, "git_revision": "df783370290251e94d093b00cd2199f2cfcd7480", "ctags": [{"_type": "tag", "name": "_ensurePersonaDraftsPersonaIdColumnMysql", "path": "/home/kavia/workspace/code-generation/career-navigator-server/express_backend/src/db/schemaSelfHeal.js", "pattern": "/^async function _ensurePersonaDraftsPersonaIdColumnMysql() {$/", "language": "JavaScript", "kind": "function", "signature": "()"}, {"_type": "tag", "name": "_ensurePersonaFinalPersonaIdColumnMysql", "path": "/home/kavia/workspace/code-generation/career-navigator-server/express_backend/src/db/schemaSelfHeal.js", "pattern": "/^async function _ensurePersonaFinalPersonaIdColumnMysql() {$/", "language": "JavaScript", "kind": "function", "signature": "()"}, {"_type": "tag", "name": "_mysqlHasColumn", "path": "/home/kavia/workspace/code-generation/career-navigator-server/express_backend/src/db/schemaSelfHeal.js", "pattern": "/^async function _mysqlHasColumn(tableName, columnName) {$/", "language": "JavaScript", "kind": "function", "signature": "(tableName, columnName)"}, {"_type": "tag", "name": "_mysqlHasIndex", "path": "/home/kavia/workspace/code-generation/career-navigator-server/express_backend/src/db/schemaSelfHeal.js", "pattern": "/^async function _mysqlHasIndex(tableName, indexName) {$/", "language": "JavaScript", "kind": "function", "signature": "(tableName, indexName)"}, {"_type": "tag", "name": "_mysqlHasTable", "path": "/home/kavia/workspace/code-generation/career-navigator-server/express_backend/src/db/schemaSelfHeal.js", "pattern": "/^async function _mysqlHasTable(tableName) {$/", "language": "JavaScript", "kind": "function", "signature": "(tableName)"}, {"_type": "tag", "name": "ensureMysqlSchemaCompatible", "path": "/home/kavia/workspace/code-generation/career-navigator-server/express_backend/src/db/schemaSelfHeal.js", "pattern": "/^  ensureMysqlSchemaCompatible$/", "language": "JavaScript", "kind": "field", "scope": "module.exports", "scopeKind": "class"}, {"_type": "tag", "name": "ensureMysqlSchemaCompatible", "path": "/home/kavia/workspace/code-generation/career-navigator-server/express_backend/src/db/schemaSelfHeal.js", "pattern": "/^async function ensureMysqlSchemaCompatible() {$/", "language": "JavaScript", "kind": "function", "signature": "()"}], "hash": "72ddca8ba358bef8d2d74fe7b40db845", "format-version": 4, "code-base-name": "career-navigator-server", "filename": "express_backend/src/db/schemaSelfHeal.js", "fields": [{"name": "ensureMysqlSchemaCompatible", "scope": "module.exports", "scopeKind": "class", "description": "unavailable"}], "revision_history": [{"152": "df783370290251e94d093b00cd2199f2cfcd7480"}]}