{"is_source_file": true, "format": "JavaScript", "description": "This file is a JavaScript module implementing a document extraction service for various file formats (PDF, DOCX, TXT, DOC). It provides an API function to extract text content from uploaded files, handling optional dependencies for PDF and DOCX parsing, and includes detailed metadata and warnings.", "external_files": ["pdf-parse", "mammoth"], "external_methods": ["require('pdf-parse')", "require('mammoth')"], "published": ["extractTextFromUploadedFile"], "classes": [], "methods": [{"name": "extractTextFromUploadedFile({ filename, mimeType, buffer })", "description": "Asynchronously extracts text from a file buffer based on its MIME type and filename, supporting PDF, DOCX, TXT, and DOC formats, returning extracted text, metadata, and warnings.", "scope": "", "scopeKind": ""}, {"name": "_decodeToText(buffer)", "scope": "", "scopeKind": "", "description": "unavailable"}, {"name": "_normalizeNewlines(text)", "scope": "", "scopeKind": "", "description": "unavailable"}], "calls": ["pdfParse", "mammoth.extractRawText"], "search-terms": ["extractionService", "extractTextFromUploadedFile", "pdf-parse", "mammoth", "file buffer", "text extraction", "document conversion"], "state": 2, "file_id": 81, "knowledge_revision": 414, "git_revision": "2db3c6bc92293e2b4e17b60342c80d222de7a588", "revision_history": [{"190": "8e45fc38d9f801432ebeb3b4ae96bead4f2fb834"}, {"414": "2db3c6bc92293e2b4e17b60342c80d222de7a588"}], "ctags": [{"_type": "tag", "name": "_decodeToText", "path": "/home/kavia/workspace/code-generation/career-navigator-server/express_backend/src/services/extractionService.js", "pattern": "/^function _decodeToText(buffer) {$/", "language": "JavaScript", "kind": "function", "signature": "(buffer)"}, {"_type": "tag", "name": "_normalizeNewlines", "path": "/home/kavia/workspace/code-generation/career-navigator-server/express_backend/src/services/extractionService.js", "pattern": "/^function _normalizeNewlines(text) {$/", "language": "JavaScript", "kind": "function", "signature": "(text)"}, {"_type": "tag", "name": "extractTextFromUploadedFile", "path": "/home/kavia/workspace/code-generation/career-navigator-server/express_backend/src/services/extractionService.js", "pattern": "/^export async function extractTextFromUploadedFile({ filename, mimeType, buffer }) {$/", "language": "JavaScript", "kind": "function", "signature": "({ filename, mimeType, buffer })"}, {"_type": "tag", "name": "mammoth", "path": "/home/kavia/workspace/code-generation/career-navigator-server/express_backend/src/services/extractionService.js", "pattern": "/^let mammoth = null;$/", "language": "JavaScript", "kind": "variable"}, {"_type": "tag", "name": "pdfParse", "path": "/home/kavia/workspace/code-generation/career-navigator-server/express_backend/src/services/extractionService.js", "pattern": "/^let pdfParse = null;$/", "language": "JavaScript", "kind": "variable"}, {"_type": "tag", "name": "require", "path": "/home/kavia/workspace/code-generation/career-navigator-server/express_backend/src/services/extractionService.js", "pattern": "/^const require = createRequire(import.meta.url);$/", "language": "JavaScript", "kind": "constant"}], "hash": "f302de5a68f0a140f16f7038324b2096", "format-version": 4, "code-base-name": "career-navigator-server", "filename": "express_backend/src/services/extractionService.js", "fields": [{"name": "let mammoth = null;", "scope": "", "scopeKind": "", "description": "unavailable"}, {"name": "let pdfParse = null;", "scope": "", "scopeKind": "", "description": "unavailable"}]}