{"is_source_file": true, "format": "JavaScript", "description": "This source file defines Express.js route handlers for the orchestration API endpoints in a server application. It routes HTTP requests related to starting orchestrations, running workflows, fetching build statuses, linking uploads, extracting and normalizing documents, generating persona drafts, and finalizing personas. The routes invoke methods from the orchestrationService and handle responses and errors accordingly.", "external_files": ["../services/orchestrationService.js", "../utils/errors.js"], "external_methods": ["orchestrationService.startOrchestration", "orchestrationService.runAllOrchestration", "orchestrationService.getOrchestration", "orchestrationService.linkUploadToBuild", "orchestrationService.extractAndNormalizeForBuild", "orchestrationService.generatePersonaDraftForBuild", "orchestrationService.finalizePersonaForBuild", "sendError"], "published": ["router"], "classes": [], "methods": [{"name": "router.post('/start')", "description": "Starts a new orchestration session, creating a build/workflow."}, {"name": "router.post('/run-all')", "description": "Runs the full build workflow end-to-end, including upload, extraction, normalization, and persona drafting."}, {"name": "router.get('/builds/:id')", "description": "Retrieves the orchestration record for a specific build ID."}, {"name": "router.post('/builds/:id/link-upload')", "description": "Links uploaded files and documents to an existing build."}, {"name": "router.post('/builds/:id/extract-normalize')", "description": "Derives normalized text from linked documents for a specific build."}, {"name": "router.post('/builds/:id/generate-draft')", "description": "Generates a persona draft based on normalized text."}, {"name": "router.post('/builds/:id/finalize')", "description": "Finalizes the persona, saving the final blob and creating a new version if needed."}], "calls": ["orchestrationService.startOrchestration", "orchestrationService.runAllOrchestration", "orchestrationService.getOrchestration", "orchestrationService.linkUploadToBuild", "orchestrationService.extractAndNormalizeForBuild", "orchestrationService.generatePersonaDraftForBuild", "orchestrationService.finalizePersonaForBuild", "sendError"], "search-terms": ["orchestration", "builds", "workflow", "schema validation", "API endpoints", "express.Router", "language:JavaScript"], "state": 2, "file_id": 106, "knowledge_revision": 387, "git_revision": "317432dfd6081a326b6f492c59b8aad65f1ccfa1", "revision_history": [{"203": "284e916c6035556e1be2b84355724b106badca5d"}, {"387": "317432dfd6081a326b6f492c59b8aad65f1ccfa1"}], "ctags": [{"_type": "tag", "name": "router", "path": "/home/kavia/workspace/code-generation/career-navigator-server/express_backend/src/routes/orchestration.js", "pattern": "/^const router = express.Router();$/", "language": "JavaScript", "kind": "constant"}], "hash": "2cb7754397e31eb086846e8306e3200e", "format-version": 4, "code-base-name": "career-navigator-server", "filename": "express_backend/src/routes/orchestration.js"}